toybricks/__init__.py
toybricks-0.0.0.dist-info/LICENSE
toybricks-0.0.0.dist-info/METADATA
toybricks-0.0.0.dist-info/WHEEL
toybricks-0.0.0.dist-info/top_level.txt
toybricks-0.0.0.dist-info/RECORD
