Metadata-Version: 2.1
Name: toybricks
Version: 0.0.0
Summary: A package designed to provide a unified framework for Neural Architecture Search. Under internal testing.
Author-email: Muhan Xiao <syrupcake@protonmail.com>
License: MIT License
Classifier: License :: OSI Approved :: MIT License
Classifier: Programming Language :: Python :: 3
Classifier: Programming Language :: Python :: 3.10
Classifier: Programming Language :: Python :: 3.11
Requires-Python: >=3.10
License-File: LICENSE
